romav2/__init__.py
romav2/benchmarks/__init__.py
romav2/benchmarks/mega1500.py
romav2/benchmarks/satast.py
romav2/benchmarks/scannet1500.py
romav2/benchmarks/wxbs.py
romav2/device.py
romav2/dpt.py
romav2/features.py
romav2/geometry.py
romav2/io.py
romav2/local_correlation.py
romav2/logging.py
romav2/matcher.py
romav2/normalizers.py
romav2/refiner.py
romav2/romav2.py
romav2/types.py
romav2/vis.py
romav2/vit/__init__.py
romav2/vit/attention.py
romav2/vit/block.py
romav2/vit/ffn_layers.py
romav2/vit/layer_scale.py
romav2/vit/patch_embed.py
romav2/vit/rms_norm.py
romav2/vit/rope.py
romav2/vit/rope_mixed.py
romav2/vit/utils.py
romav2-2.0.0.dist-info/WHEEL
romav2-2.0.0.dist-info/METADATA
romav2-2.0.0.dist-info/RECORD
