Metadata-Version: 2.3
Name: romav2
Version: 2.0.0
Summary: RoMa v2: Harder Better Faster Denser Feature Matching
Author: Johan Edstedt
Author-email: Johan Edstedt <johan.edstedt@liu.se>
Requires-Dist: dataclasses>=0.8
Requires-Dist: einops>=0.8.1
Requires-Dist: pillow>=12.0.0
Requires-Dist: rich>=14.2.0
Requires-Dist: torch
Requires-Dist: torchvision>=0.23.0
Requires-Dist: tqdm>=4.67.1
Requires-Dist: slurm-util>=0.2.7 ; extra == 'dev'
Requires-Dist: ruff>=0.14.5 ; extra == 'dev'
Requires-Dist: kornia>=0.8.2 ; extra == 'eval'
Requires-Dist: matplotlib>=3.10.7 ; extra == 'eval'
Requires-Dist: opencv-python>=4.12.0.88 ; extra == 'eval'
Requires-Dist: wandb>=0.23.0 ; extra == 'eval'
Requires-Dist: wxbs-benchmark>=0.0.4 ; extra == 'eval'
Requires-Dist: fused-local-corr ; sys_platform == 'linux' and extra == 'fused-local-corr'
Requires-Python: >=3.10
Provides-Extra: dev
Provides-Extra: eval
Provides-Extra: fused-local-corr
